elifecleaner/__init__.py
elifecleaner/assessment_terms.py
elifecleaner/block.py
elifecleaner/equation.py
elifecleaner/fig.py
elifecleaner/parse.py
elifecleaner/pdf_utils.py
elifecleaner/prc.py
elifecleaner/pub_history.py
elifecleaner/sub_article.py
elifecleaner/table.py
elifecleaner/transform.py
elifecleaner/utils.py
elifecleaner/video.py
elifecleaner/video_xml.py
elifecleaner/zip_lib.py
elifecleaner-0.84.0.dist-info/LICENSE
elifecleaner-0.84.0.dist-info/METADATA
elifecleaner-0.84.0.dist-info/WHEEL
elifecleaner-0.84.0.dist-info/top_level.txt
elifecleaner-0.84.0.dist-info/RECORD
