Metadata-Version: 2.1
Name: elifecleaner
Version: 0.84.0
Summary: Clean and transform article submission files into a consistent format.
Home-page: https://github.com/elifesciences/elife-cleaner
Maintainer: eLife Sciences Publications Ltd.
Maintainer-email: tech-team@elifesciences.org
License: MIT
Classifier: Development Status :: 3 - Alpha
Classifier: Intended Audience :: Developers
Classifier: License :: OSI Approved :: MIT License
Classifier: Programming Language :: Python :: 3.6
License-File: LICENSE
Requires-Dist: docmaptools >=0.26.0
Requires-Dist: elifetools >=0.40.0
Requires-Dist: elifearticle >=0.20.0
Requires-Dist: jatsgenerator >=0.16.0
Requires-Dist: PyYAML >=5.4.1
Requires-Dist: wand >=0.5.2
